nigerian_states/__init__.py
nigerian_states/admin.py
nigerian_states/apps.py
nigerian_states/enums.py
nigerian_states/fields.py
nigerian_states/forms.py
nigerian_states/models.py
nigerian_states/utils.py
nigerian_states/views.py
nigerian_states/fixtures/fixtures.json
nigerian_states/templatetags/state_tags.py
nigerian_states/templatetags/__pycache__/default_tags.cpython-310.pyc
nigerian_states/templatetags/__pycache__/state_tags.cpython-310.pyc
django_nigerian_states-1.0.dist-info/LICENSE
django_nigerian_states-1.0.dist-info/METADATA
django_nigerian_states-1.0.dist-info/WHEEL
django_nigerian_states-1.0.dist-info/top_level.txt
django_nigerian_states-1.0.dist-info/RECORD
