Metadata-Version: 2.1
Name: django_nigerian_states
Version: 1.0
Summary: Django Nigerian States is a comprehensive third-party Django application that provides a robust and efficient way to manage and interact with geopolitical data related to Nigeria.
Home-page: https://github.com/Afeez1131/django-nigerian-state
Author: Afeez Lawal
Author-email: lawalafeez052@gmail.com
License: MIT
Classifier: Environment :: Web Environment
Classifier: Framework :: Django
Classifier: Framework :: Django :: 5.0
Classifier: Intended Audience :: Developers
Classifier: License :: OSI Approved :: MIT License
Classifier: Operating System :: OS Independent
Classifier: Programming Language :: Python
Classifier: Programming Language :: Python :: 3
Classifier: Programming Language :: Python :: 3 :: Only
Classifier: Programming Language :: Python :: 3.10
Classifier: Programming Language :: Python :: 3.11
Classifier: Programming Language :: Python :: 3.12
Classifier: Topic :: Internet :: WWW/HTTP
Classifier: Topic :: Internet :: WWW/HTTP :: Dynamic Content
Requires-Python: >=3.10
License-File: LICENSE
Requires-Dist: Django >=5.0
